Workbook

Sheet Sales Sheet 1
A1: SALARY SHEET
A2: S:NO | B2: Employee Name | C2: Basic Salary | D2: DA 10% | E2: HRA 15% | F2: Gross Salary (CTC) | G2: PF 5% | H2: Net Salary (In Hand)
A3: 1 | B3: Silviya Angel | C3: 25000 | D3: =C3*10% -> 2500 | E3: =C3*15% -> 3750 | F3: =SUM(C3:E3) -> 31250 | G3: =C3*5% -> 1250 | H3: =F3-G3 -> 30000
A4: 2 | B4: Bhuvana | C4: 24500 | D4: =C4*10% -> 2450 | E4: =C4*15% -> 3675 | F4: =SUM(C4:E4) -> 30625 | G4: =C4*5% -> 1225 | H4: =F4-G4 -> 29400
A5: 3 | B5: Nandhini | C5: 24000 | D5: =C5*10% -> 2400 | E5: =C5*15% -> 3600 | F5: =SUM(C5:E5) -> 30000 | G5: =C5*5% -> 1200 | H5: =F5-G5 -> 28800
A6: 4 | B6: priya | C6: 23500 | D6: =C6*10% -> 2350 | E6: =C6*15% -> 3525 | F6: =SUM(C6:E6) -> 29375 | G6: =C6*5% -> 1175 | H6: =F6-G6 -> 28200
A7: 5 | B7: Ashwini | C7: 23000 | D7: =C7*10% -> 2300 | E7: =C7*15% -> 3450 | F7: =SUM(C7:E7) -> 28750 | G7: =C7*5% -> 1150 | H7: =F7-G7 -> 27600
A8: 6 | B8: Preethi | C8: 22500 | D8: =C8*10% -> 2250 | E8: =C8*15% -> 3375 | F8: =SUM(C8:E8) -> 28125 | G8: =C8*5% -> 1125 | H8: =F8-G8 -> 27000
A9: 7 | B9: Sudhan | C9: 22000 | D9: =C9*10% -> 2200 | E9: =C9*15% -> 3300 | F9: =SUM(C9:E9) -> 27500 | G9: =C9*5% -> 1100 | H9: =F9-G9 -> 26400
A10: 8 | B10: Kumar | C10: 21500 | D10: =C10*10% -> 2150 | E10: =C10*15% -> 3225 | F10: =SUM(C10:E10) -> 26875 | G10: =C10*5% -> 1075 | H10: =F10-G10 -> 25800
A11: 9 | B11: Raghul | C11: 21000 | D11: =C11*10% -> 2100 | E11: =C11*15% -> 3150 | F11: =SUM(C11:E11) -> 26250 | G11: =C11*5% -> 1050 | H11: =F11-G11 -> 25200
A12: 10 | B12: Charan | C12: 20500 | D12: =C12*10% -> 2050 | E12: =C12*15% -> 3075 | F12: =SUM(C12:E12) -> 25625 | G12: =C12*5% -> 1025 | H12: =F12-G12 -> 24600
A13: 11 | B13: Prem | C13: 20000 | D13: =C13*10% -> 2000 | E13: =C13*15% -> 3000 | F13: =SUM(C13:E13) -> 25000 | G13: =C13*5% -> 1000 | H13: =F13-G13 -> 24000
A14: 12 | B14: Arun | C14: 25500 | D14: =C14*10% -> 2550 | E14: =C14*15% -> 3825 | F14: =SUM(C14:E14) -> 31875 | G14: =C14*5% -> 1275 | H14: =F14-G14 -> 30600

Sheet Sales Sheet 2
A1: SALARY SHEET
A2: S:NO | B2: Employee Name | C2: Basic Salary | D2: DA 10% | E2: HRA 15% | F2: Gross Salary (CTC) | G2: PF 5% | H2: Net Salary (In Hand)
A3: 1 | B3: Silviya Angel | C3: 25000 | D3: =C3*10% -> 2500 | E3: =C3*15% -> 3750 | F3: =SUM(C3:E3) -> 31250 | G3: =C3*5% -> 1250 | H3: =F3-G3 -> 30000
A4: 2 | B4: Bhuvana | C4: 24500 | D4: =C4*10% -> 2450 | E4: =C4*15% -> 3675 | F4: =SUM(C4:E4) -> 30625 | G4: =C4*5% -> 1225 | H4: =F4-G4 -> 29400
A5: 3 | B5: Nandhini | C5: 24000 | D5: =C5*10% -> 2400 | E5: =C5*15% -> 3600 | F5: =SUM(C5:E5) -> 30000 | G5: =C5*5% -> 1200 | H5: =F5-G5 -> 28800
A6: 4 | B6: priya | C6: 23500 | D6: =C6*10% -> 2350 | E6: =C6*15% -> 3525 | F6: =SUM(C6:E6) -> 29375 | G6: =C6*5% -> 1175 | H6: =F6-G6 -> 28200
A7: 5 | B7: Ashwini | C7: 23000 | D7: =C7*10% -> 2300 | E7: =C7*15% -> 3450 | F7: =SUM(C7:E7) -> 28750 | G7: =C7*5% -> 1150 | H7: =F7-G7 -> 27600
A8: 6 | B8: Preethi | C8: 22500 | D8: =C8*10% -> 2250 | E8: =C8*15% -> 3375 | F8: =SUM(C8:E8) -> 28125 | G8: =C8*5% -> 1125 | H8: =F8-G8 -> 27000
A9: 7 | B9: Sudhan | C9: 22000 | D9: =C9*10% -> 2200 | E9: =C9*15% -> 3300 | F9: =SUM(C9:E9) -> 27500 | G9: =C9*5% -> 1100 | H9: =F9-G9 -> 26400
A10: 8 | B10: Kumar | C10: 21500 | D10: =C10*10% -> 2150 | E10: =C10*15% -> 3225 | F10: =SUM(C10:E10) -> 26875 | G10: =C10*5% -> 1075 | H10: =F10-G10 -> 25800
A11: 9 | B11: Raghul | C11: 21000 | D11: =C11*10% -> 2100 | E11: =C11*15% -> 3150 | F11: =SUM(C11:E11) -> 26250 | G11: =C11*5% -> 1050 | H11: =F11-G11 -> 25200
A12: 10 | B12: Charan | C12: 20500 | D12: =C12*10% -> 2050 | E12: =C12*15% -> 3075 | F12: =SUM(C12:E12) -> 25625 | G12: =C12*5% -> 1025 | H12: =F12-G12 -> 24600
A13: 11 | B13: Prem | C13: 20000 | D13: =C13*10% -> 2000 | E13: =C13*15% -> 3000 | F13: =SUM(C13:E13) -> 25000 | G13: =C13*5% -> 1000 | H13: =F13-G13 -> 24000
A14: 12 | B14: Arun | C14: 25500 | D14: =C14*10% -> 2550 | E14: =C14*15% -> 3825 | F14: =SUM(C14:E14) -> 31875 | G14: =C14*5% -> 1275 | H14: =F14-G14 -> 30600
... A32: 30 | B32: Aishwarya | C32: 37000 | D32: =C32*10% -> 3700 | E32: =C32*15% -> 5550 | F32: =SUM(C32:E32) -> 46250 | G32: =C32*5% -> 1850 | H32: =F32-G32 -> 44400

Sheet MATHEMATICAL FUNCTIONS
A1: MATHEMATICAL FUNCTION
A2: S.NO | B2: NAME | C2: TAMIL | D2: ENGLISH | E2: MATHS | F2: SCIENCE | G2: SOCIAL | H2: TOTAL | I2: AVERAGE | J2: MEDIAN | K2: MODE | L2: COUNT | M2: PERCENTAGE | N2: MIN | O2: MAX
A3: 1 | B3: Priya | C3: 85 | D3: 80 | E3: 99 | F3: 80 | G3: 80 | H3: =SUM(C3:G3) -> 424 | I3: =AVERAGE(C3:G3) -> 84.8 | J3: =MEDIAN(C3:G3) -> 80 | K3: =MODE(C3:G3) -> 80 | L3: =COUNT(C3:G3) -> 5 | M3: =H3/500 -> 0.848 | N3: =MIN(C3:G3) -> 80 | O3: =MAX(C3:G3) -> 99
A4: 2 | B4: Renuga | C4: 90 | D4: 80 | E4: 75 | F4: 95 | G4: 80 | H4: =SUM(C4:G4) -> 420 | I4: =AVERAGE(C4:G4) -> 84 | J4: =MEDIAN(C4:G4) -> 80 | K4: =MODE(C4:G4) -> 80 | L4: =COUNT(C4:G4) -> 5 | M4: =H4/500 -> 0.84 | N4: =MIN(C4:G4) -> 75 | O4: =MAX(C4:G4) -> 95 | S4: PERCENTAGE FUNCTION
A5: 3 | B5: Nandhini | C5: 90 | D5: 75 | E5: 73 | F5: 90 | G5: 96 | H5: =SUM(C5:G5) -> 424 | I5: =AVERAGE(C5:G5) -> 84.8 | J5: =MEDIAN(C5:G5) -> 90 | K5: =MODE(C5:G5) -> 90 | L5: =COUNT(C5:G5) -> 5 | M5: =H5/500 -> 0.848 | N5: =MIN(C5:G5) -> 73 | O5: =MAX(C5:G5) -> 96 | S5: TAMIL | T5: ENGLISH | U5: TOTAL | V5: PERCENTAGE %
A6: 4 | B6: Abi | C6: 95 | D6: 80 | E6: 75 | F6: 92 | G6: 90 | H6: =SUM(C6:G6) -> 432 | I6: =AVERAGE(C6:G6) -> 86.4 | J6: =MEDIAN(C6:G6) -> 90 | K6: =MODE(C6:G6) -> #N/A | L6: =COUNT(C6:G6) -> 5 | M6: =H6/500 -> 0.864 | N6: =MIN(C6:G6) -> 75 | O6: =MAX(C6:G6) -> 95 | S6: 74 | T6: 84 | U6: =SUM(S6:T6) -> 158 | V6: =U6/200 -> 0.79
A7: 5 | B7: Lavanya | C7: 80 | D7: 85 | E7: 70 | F7: 82 | G7: 86 | H7: =SUM(C7:G7) -> 403 | I7: =AVERAGE(C7:G7) -> 80.6 | J7: =MEDIAN(C7:G7) -> 82 | K7: =MODE(C7:G7) -> #N/A | L7: =COUNT(C7:G7) -> 5 | M7: =H7/500 -> 0.806 | N7: =MIN(C7:G7) -> 70 | O7: =MAX(C7:G7) -> 86 | S7: 73 | T7: 83 | U7: =SUM(S7:T7) -> 156 | V7: =U7/200 -> 0.78
A8: 6 | B8: Divya | C8: 95 | D8: 90 | E8: 92 | F8: 89 | G8: 84 | H8: =SUM(C8:G8) -> 450 | I8: =AVERAGE(C8:G8) -> 90 | J8: =MEDIAN(C8:G8) -> 90 | K8: =MODE(C8:G8) -> #N/A | L8: =COUNT(C8:G8) -> 5 | M8: =H8/500 -> 0.9 | N8: =MIN(C8:G8) -> 84 | O8: =MAX(C8:G8) -> 95
A9: 7 | B9: Mini | C9: 85 | D9: 80 | E9: 78 | F9: 81 | G9: 79 | H9: =SUM(C9:G9) -> 403 | I9: =AVERAGE(C9:G9) -> 80.6 | J9: =MEDIAN(C9:G9) -> 80 | K9: =MODE(C9:G9) -> #N/A | L9: =COUNT(C9:G9) -> 5 | M9: =H9/500 -> 0.806 | N9: =MIN(C9:G9) -> 78 | O9: =MAX(C9:G9) -> 85
A10: 8 | B10: Malar | C10: 90 | D10: 90 | E10: 93 | F10: 90 | G10: 87 | H10: =SUM(C10:G10) -> 450 | I10: =AVERAGE(C10:G10) -> 90 | J10: =MEDIAN(C10:G10) -> 90 | K10: =MODE(C10:G10) -> 90 | L10: =COUNT(C10:G10) -> 5 | M10: =H10/500 -> 0.9 | N10: =MIN(C10:G10) -> 87 | O10: =MAX(C10:G10) -> 93 | S10: MIN FUNCTION
A11: 9 | B11: Sankari | C11: 90 | D11: 85 | E11: 85 | F11: 87 | G11: 89 | H11: =SUM(C11:G11) -> 436 | I11: =AVERAGE(C11:G11) -> 87.2 | J11: =MEDIAN(C11:G11) -> 87 | K11: =MODE(C11:G11) -> 85 | L11: =COUNT(C11:G11) -> 5 | M11: =H11/500 -> 0.872 | N11: =MIN(C11:G11) -> 85 | O11: =MAX(C11:G11) -> 90 | S11: 75 | T11: 85 | U11: 95 | V11: =MIN(S11:U11) -> 75
A12: 10 | B12: Dharshini | C12: 85 | D12: 80 | E12: 97 | F12: 83 | G12: 82 | H12: =SUM(C12:G12) -> 427 | I12: =AVERAGE(C12:G12) -> 85.4 | J12: =MEDIAN(C12:G12) -> 83 | K12: =MODE(C12:G12) -> #N/A | L12: =COUNT(C12:G12) -> 5 | M12: =H12/500 -> 0.854 | N12: =MIN(C12:G12) -> 80 | O12: =MAX(C12:G12) -> 97 | S12: 74 | T12: 84 | U12: 94 | V12: =MIN(S12:U12) -> 74
A13: 11 | B13: Rathi | C13: 98 | D13: 99 | E13: 100 | F13: 97 | G13: 92 | H13: =SUM(C13:G13) -> 486 | I13: =AVERAGE(C13:G13) -> 97.2 | J13: =MEDIAN(C13:G13) -> 98 | K13: =MODE(C13:G13) -> #N/A | L13: =COUNT(C13:G13) -> 5 | M13: =H13/500 -> 0.972 | N13: =MIN(C13:G13) -> 92 | O13: =MAX(C13:G13) -> 100 | S13: 73 | T13: 83 | U13: 93 | V13: =MIN(S13:U13) -> 73
A14: 12 | B14: Janani | C14: 90 | D14: 95 | E14: 90 | F14: 89 | G14: 85 | H14: =SUM(C14:G14) -> 449 | I14: =AVERAGE(C14:G14) -> 89.8 | J14: =MEDIAN(C14:G14) -> 90 | K14: =MODE(C14:G14) -> 90 | L14: =COUNT(C14:G14) -> 5 | M14: =H14/500 -> 0.898 | N14: =MIN(C14:G14) -> 85 | O14: =MAX(C14:G14) -> 95
A15: 13 | B15: Lalitha | C15: 80 | D15: 90 | E15: 80 | F15: 86 | G15: 83 | H15: =SUM(C15:G15) -> 419 | I15: =AVERAGE(C15:G15) -> 83.8 | J15: =MEDIAN(C15:G15) -> 83 | K15: =MODE(C15:G15) -> 80 | L15: =COUNT(C15:G15) -> 5 | M15: =H15/500 -> 0.838 | N15: =MIN(C15:G15) -> 80 | O15: =MAX(C15:G15) -> 90
A16: 14 | B16: Pavithra | C16: 80 | D16: 80 | E16: 80 | F16: 88 | G16: 81 | H16: =SUM(C16:G16) -> 409 | I16: =AVERAGE(C16:G16) -> 81.8 | J16: =MEDIAN(C16:G16) -> 80 | K16: =MODE(C16:G16) -> 80 | L16: =COUNT(C16:G16) -> 5 | M16: =H16/500 -> 0.818 | N16: =MIN(C16:G16) -> 80 | O16: =MAX(C16:G16) -> 88 | S16: MAX FUNCTION
A17: 15 | B17: Vanitha | C17: 85 | D17: 85 | E17: 95 | F17: 86 | G17: 82 | H17: =SUM(C17:G17) -> 433 | I17: =AVERAGE(C17:G17) -> 86.6 | J17: =MEDIAN(C17:G17) -> 85 | K17: =MODE(C17:G17) -> 85 | L17: =COUNT(C17:G17) -> 5 | M17: =H17/500 -> 0.866 | N17: =MIN(C17:G17) -> 82 | O17: =MAX(C17:G17) -> 95 | S17: 55 | T17: 65 | U17: 75 | V17: =MAX(S17:U17) -> 75
A18: 16 | B18: Devi | C18: 80 | D18: 80 | E18: 78 | F18: 78 | G18: 86 | H18: =SUM(C18:G18) -> 402 | I18: =AVERAGE(C18:G18) -> 80.4 | J18: =MEDIAN(C18:G18) -> 80 | K18: =MODE(C18:G18) -> 80 | L18: =COUNT(C18:G18) -> 5 | M18: =H18/500 -> 0.804 | N18: =MIN(C18:G18) -> 78 | O18: =MAX(C18:G18) -> 86 | S18: 56 | T18: 66 | U18: 76 | V18: =MAX(S18:U18) -> 76
A19: 17 | B19: Sathya | C19: 85 | D19: 80 | E19: 79 | F19: 83 | G19: 81 | H19: =SUM(C19:G19) -> 408 | I19: =AVERAGE(C19:G19) -> 81.6 | J19: =MEDIAN(C19:G19) -> 81 | K19: =MODE(C19:G19) -> #N/A | L19: =COUNT(C19:G19) -> 5 | M19: =H19/500 -> 0.816 | N19: =MIN(C19:G19) -> 79 | O19: =MAX(C19:G19) -> 85 | S19: 57 | T19: 67 | U19: 77 | V19: =MAX(S19:U19) -> 77
A20: 18 | B20: Lekha | C20: 85 | D20: 90 | E20: 85 | F20: 82 | G20: 85 | H20: =SUM(C20:G20) -> 427 | I20: =AVERAGE(C20:G20) -> 85.4 | J20: =MEDIAN(C20:G20) -> 85 | K20: =MODE(C20:G20) -> 85 | L20: =COUNT(C20:G20) -> 5 | M20: =H20/500 -> 0.854 | N20: =MIN(C20:G20) -> 82 | O20: =MAX(C20:G20) -> 90
A21: 19 | B21: Amesha | C21: 80 | D21: 80 | E21: 76 | F21: 78 | G21: 84 | H21: =SUM(C21:G21) -> 398 | I21: =AVERAGE(C21:G21) -> 79.6 | J21: =MEDIAN(C21:G21) -> 80 | K21: =MODE(C21:G21) -> 80 | L21: =COUNT(C21:G21) -> 5 | M21: =H21/500 -> 0.796 | N21: =MIN(C21:G21) -> 76 | O21: =MAX(C21:G21) -> 84
A22: 20 | B22: Mohan | C22: 90 | D22: 95 | E22: 80 | F22: 93 | G22: 87 | H22: =SUM(C22:G22) -> 445 | I22: =AVERAGE(C22:G22) -> 89 | J22: =MEDIAN(C22:G22) -> 90 | K22: =MODE(C22:G22) -> #N/A | L22: =COUNT(C22:G22) -> 5 | M22: =H22/500 -> 0.89 | N22: =MIN(C22:G22) -> 80 | O22: =MAX(C22:G22) -> 95
C26: SUM FUNCTION | H26: AVERAGE FUNCTION | M26: MODE FUNCTION
C27: 78 | D27: 83 | E27: 65 | F27: =SUM(C27+D27+E27) -> 226 | H27: 75 | I27: 85 | J27: 95 | K27: =AVERAGE(H27:J27) -> 85 | M27: 80 | N27: 84 | O27: =MODE(M27:N27) -> #N/A
C28: 81 | D28: 73 | E28: 87 | F28: =SUM(C28+D28+E28) -> 241 | H28: 74 | I28: 84 | J28: 94 | K28: =AVERAGE(H28:J28) -> 84 | M28: 65 | N28: 67 | O28: =MODE(M28:N28) -> #N/A
C29: 72 | D29: 67 | E29: 82 | F29: =SUM(C29+D29+E29) -> 221 | H29: 73 | I29: 83 | J29: 93 | K29: =AVERAGE(H29:J29) -> 83 | M29: 70 | N29: 75 | O29: =MODE(M29:N29) -> #N/A
C32: SUM FUNCTION | H32: MEDIAN FUNCTION | M32: COUNT FUNCTION
C33: 75 | D33: 81 | E33: 62 | F33: =SUM(C33:E33) -> 218 | H33: 55 | I33: 65 | J33: 75 | K33: =MEDIAN(H33:J33) -> 65 | M33: 78 | N33: 83 | O33: =COUNT(M33:N33) -> 2
C34: 79 | D34: 75 | E34: 84 | F34: =SUM(C34:E34) -> 238 | H34: 56 | I34: 66 | J34: 76 | K34: =MEDIAN(H34:J34) -> 66 | M34: 81 | N34: 73 | O34: =COUNT(M34:N34) -> 2
C35: 76 | D35: 69 | E35: 83 | F35: =SUM(C35:E35) -> 228 | H35: 57 | I35: 67 | J35: 77 | K35: =MEDIAN(H35:J35) -> 67 | M35: 72 | N35: 67 | O35: =COUNT(M35:N35) -> 2

Sheet IF CONDITIONAL FUNCTIONS
A1: IF CONDITION | K1: IFS CONDITION
F2: SUBRACTION
A3: A(NAME) | B3: B(SALES) | C3: GOOD/BAD | D3: DISCOUNT | F3: 20 | G3: 90 | H3: =IF(F3<=G3,(G3-F3),(F3-G3)) -> 70 | K3: NAME | L3: TAMIL | M3: ENGLISH | N3: MATHS | O3: SCIENCE | P3: SOCIAL | Q3: G TAMIL | R3: G ENG | S3: G MATHS | T3: G SCIENCE | U3: G SOCIAL
A4: Arun | B4: 60000 | C4: =IF(B4>=50000,"good","bad") -> good | D4: =IF(B4>50000,B4-(B4*10%),B4) -> 54000 | F4: 30 | G4: 45 | H4: =IF(F4<=G4,(G4-F4),(F4-G4)) -> 15 | K4: DIVYA | L4: 90 | M4: 76 | N4: 68 | O4: 79 | P4: 89 | Q4: {=_xlfn.IFS(L4:P4<=50,"D",L4:P4<=70,"C",L4:P4<=80,"B",L4:P4<=90,"A",L4:P4<=95,"A+")} -> A | R4: B | S4: C | T4: B | U4: A
A5: Nisha | B5: 70000 | C5: =IF(B5>=50000,"good","bad") -> good | D5: =IF(B5>50000,B5-(B5*10%),B5) -> 63000 | F5: 585 | G5: 800 | H5: =IF(F5<=G5,(G5-F5),(F5-G5)) -> 215 | K5: OVIYA | L5: 60 | M5: 87 | N5: 76 | O5: 58 | P5: 67 | Q5: {=_xlfn.IFS(L5:P5<=50,"D",L5:P5<=70,"C",L5:P5<=80,"B",L5:P5<=90,"A",L5:P5<=95,"A+")} -> C | R5: A | S5: B | T5: C | U5: C
A6: Pavi | B6: 40000 | C6: =IF(B6>=50000,"good","bad") -> bad | D6: =IF(B6>50000,B6-(B6*10%),B6) -> 40000 | F6: 700 | G6: 483 | H6: =IF(F6<=G6,(G6-F6),(F6-G6)) -> 217 | K6: PRIYA | L6: 50 | M6: 94 | N6: 89 | O6: 65 | P6: 95 | Q6: {=_xlfn.IFS(L6:P6<=50,"D",L6:P6<=70,"C",L6:P6<=80,"B",L6:P6<=90,"A",L6:P6<=95,"A+")} -> D | R6: A+ | S6: A | T6: C | U6: A+
C7: To Find Sales Are Good or Bad | D7: Discount 10% | F7: 38 | G7: 628 | H7: =IF(F7<=G7,(G7-F7),(F7-G7)) -> 590 | K7: POOJA | L7: 78 | M7: 89 | N7: 90 | O7: 87 | P7: 87 | Q7: {=_xlfn.IFS(L7:P7<=50,"D",L7:P7<=70,"C",L7:P7<=80,"B",L7:P7<=90,"A",L7:P7<=95,"A+")} -> B | R7: A | S7: A | T7: A | U7: A
A10: IF AND CONDITION | O10: IF OR CONDITION
A12: NAME | B12: TAMIL | C12: ENGLISH | D12: MATHS | E12: SCIENCE | F12: SOCIAL | G12: PASS OR FAIL | I12: ITEMS | J12: PS/2020 | K12: PS/2021 | L12: PS/2022 | M12: GOOD/BAD | O12: NAME | P12: TAMIL | Q12: ENGLISH | R12: MATHS | S12: SCIENCE | T12: SOCIAL | U12: PASS/FAIL
A13: Silviya | B13: 95 | C13: 96 | D13: 88 | E13: 98 | F13: 99 | G13: {=IF(AND(B13:F13>=50),"pass","fail")} -> pass | I13: Apple | J13: 50 | K13: 60 | L13: 70 | M13: =IF(AND(J13>=50,K13>=90,L13>=65),"good","bad") -> bad | O13: Arun | P13: 80 | Q13: 70 | R13: 60 | S13: 90 | T13: 50 | U13: {=IF(OR(P13:T13>=50),"pass","fail")} -> pass
A14: Kaviya | B14: 88 | C14: 99 | D14: 65 | E14: 75 | F14: 82 | G14: {=IF(AND(B14:F14>=50),"pass","fail")} -> pass | I14: Ball | J14: 70 | K14: 80 | L14: 100 | M14: =IF(AND(J14>=50,K14>=90,L14>=65),"good","bad") -> bad | O14: Nisha | P14: 65 | Q14: 85 | R14: 75 | S14: 95 | T14: 55 | U14: {=IF(OR(P14:T14>=50),"pass","fail")} -> pass
A15: Priya | B15: 99 | C15: 87 | D15: 88 | E15: 95 | F15: 98 | G15: {=IF(AND(B15:F15>=50),"pass","fail")} -> pass | I15: Can | J15: 65 | K15: 95 | L15: 85 | M15: =IF(AND(J15>=50,K15>=90,L15>=65),"good","bad") -> good | O15: Priya | P15: 48 | Q15: 49 | R15: 46 | S15: 44 | T15: 43 | U15: {=IF(OR(P15:T15>=50),"pass","fail")} -> fail
A16: Bhuvana | B16: 89 | C16: 79 | D16: 99 | E16: 95 | F16: 87 | G16: {=IF(AND(B16:F16>=50),"pass","fail")} -> pass | I16: Doll | J16: 120 | K16: 150 | L16: 180 | M16: =IF(AND(J16>=50,K16>=90,L16>=65),"good","bad") -> good | O16: Swetha | P16: 89 | Q16: 79 | R16: 68 | S16: 84 | T16: 76 | U16: {=IF(OR(P16:T16>=50),"pass","fail")} -> pass
A17: Merlin | B17: 98 | C17: 88 | D17: 77 | E17: 93 | F17: 87 | G17: {=IF(AND(B17:F17>=50),"pass","fail")} -> pass | I17: Egg | J17: 130 | K17: 170 | L17: 140 | M17: =IF(AND(J17>=50,K17>=90,L17>=65),"good","bad") -> good | O17: Varun | P17: 76 | Q17: 77 | R17: 98 | S17: 87 | T17: 69 | U17: {=IF(OR(P17:T17>=50),"pass","fail")} -> pass
A19: IF RANK CONDITION
A21: NAME | B21: TAMIL | C21: ENGLISH | D21: MATHS | E21: SCIENCE | F21: SOCIAL | G21: TOTAL | H21: PASS OR FAIL | I21: RANK
A22: Silviya | B22: 95 | C22: 96 | D22: 88 | E22: 98 | F22: 99 | G22: =SUM(B22:F22) -> 476 | H22: {=IF(OR(B22:F22>=50),"pass","fail")} -> pass | I22: =IF(H22="PASS",RANK(G22,G22:G31,0),"NO RANK") -> 1
A23: Kaviya | B23: 88 | C23: 99 | D23: 65 | E23: 75 | F23: 82 | G23: =SUM(B23:F23) -> 409 | H23: {=IF(OR(B23:F23>=50),"pass","fail")} -> pass | I23: =IF(H23="PASS",RANK(G23,G23:G32,0),"NO RANK") -> 4
A24: Priya | B24: 99 | C24: 87 | D24: 88 | E24: 95 | F24: 98 | G24: =SUM(B24:F24) -> 467 | H24: {=IF(OR(B24:F24>=50),"pass","fail")} -> pass | I24: =IF(H24="PASS",RANK(G24,G24:G33,0),"NO RANK") -> 1
A25: Bhuvana | B25: 89 | C25: 79 | D25: 99 | E25: 95 | F25: 87 | G25: =SUM(B25:F25) -> 449 | H25: {=IF(OR(B25:F25>=50),"pass","fail")} -> pass | I25: =IF(H25="PASS",RANK(G25,G25:G34,0),"NO RANK") -> 1
A26: Merlin | B26: 98 | C26: 88 | D26: 77 | E26: 93 | F26: 87 | G26: =SUM(B26:F26) -> 443 | H26: {=IF(OR(B26:F26>=50),"pass","fail")} -> pass | I26: =IF(H26="PASS",RANK(G26,G26:G35,0),"NO RANK") -> 1
A27: Arun | B27: 80 | C27: 70 | D27: 60 | E27: 90 | F27: 50 | G27: =SUM(B27:F27) -> 350 | H27: {=IF(OR(B27:F27>=50),"pass","fail")} -> pass | I27: =IF(H27="PASS",RANK(G27,G27:G36,0),"NO RANK") -> 4
A28: Nisha | B28: 65 | C28: 85 | D28: 75 | E28: 95 | F28: 55 | G28: =SUM(B28:F28) -> 375 | H28: {=IF(OR(B28:F28>=50),"pass","fail")} -> pass | I28: =IF(H28="PASS",RANK(G28,G28:G37,0),"NO RANK") -> 3
A29: Priya | B29: 48 | C29: 49 | D29: 46 | E29: 44 | F29: 43 | G29: =SUM(B29:F29) -> 230 | H29: {=IF(OR(B29:F29>=50),"pass","fail")} -> fail | I29: =IF(H29="PASS",RANK(G29,G29:G38,0),"NO RANK") -> NO RANK
A30: Swetha | B30: 89 | C30: 79 | D30: 68 | E30: 84 | F30: 76 | G30: =SUM(B30:F30) -> 396 | H30: {=IF(OR(B30:F30>=50),"pass","fail")} -> pass | I30: =IF(H30="PASS",RANK(G30,G30:G39,0),"NO RANK") -> 2
A31: Varun | B31: 76 | C31: 77 | D31: 98 | E31: 87 | F31: 69 | G31: =SUM(B31:F31) -> 407 | H31: {=IF(OR(B31:F31>=50),"pass","fail")} -> pass | I31: =IF(H31="PASS",RANK(G31,G31:G40,0),"NO RANK") -> 1

Sheet FINANCIAL CALCULATIONS
A1: FINANCIAL CALCULATION
A3: PMT | D3: PM T
A4: PRESENT VALUE | B4: 500000 | D4: PRESENT VALUE | E4: 500000
A5: RATE | B5: 0.08 | D5: RATE | E5: 0.09
A6: NPER | B6: 60 | D6: NPER | E6: 60
A7: PMT | B7: =PMT(B5/12,B6,-B4) -> 10138.197 | D7: PMT | E7: =PMT(E5/12,E6,-E4) -> 10379.178
A9: FV | D9: PV
A10: PRESENT VALUE | B10: 5000 | D10: PMT | E10: 17088.81
A11: RATE | B11: 0.08 | D11: RATE | E11: 0.14
A12: NPER | B12: 60 | D12: NPER | E12: 36
A13: FV | B13: =FV(B11/12,B12,-B10) -> 367384.28 | D13: PV | E13: =PV(E11/12,E12,-E10) -> 499999.86
A15: NPER
A16: PRESENT VALUE | B16: 100000
A17: RATE | B17: 0.07
A18: PMT | B18: 2000
A19: NPER | B19: =NPER(B17/12,B18,-B16) -> 59.287765

Sheet TIME & DATE
A1: TIME & DATE
A2: TODAY
A3: =TODAY() -> 46308 | E3: WEEKDAYS
E4: SUNDAY IS THE FIRST DAY
A5: NOW | E5: 45920 | F5: =WEEKDAY(E5) -> 7
A6: =NOW() -> 46308.512 | E6: 38518 | F6: =WEEKDAY(E6) -> 4
E7: 41273 | F7: =WEEKDAY(E7) -> 1
A8: DATE | E8: 37360 | F8: =WEEKDAY(E8) -> 1
A9: =DATE(2026,9,5) -> 46270
E10: DATEDIF
A11: DAY | E11: 37360 | F11: 37728 | G11: =DATEDIF(E11,F11,"YD") -> 3 | H11: YEAR
A12: 46270 | B12: =DAY(A12) -> 5 | E12: 38696 | F12: 39066 | G12: =DATEDIF(E12,F12,"YD") -> 5 | H12: MONTH
E13: 28532 | F13: 28907 | G13: =DATEDIF(E13,F13,"YD") -> 10 | H13: DAYS
A14: MONTH
A15: 46270 | B15: =MONTH(A15) -> 9
A17: YEAR
A18: 46270 | B18: =YEAR(A18) -> 2026
A20: TIME
A21: =TIME(12,35,58) -> 0.52497685
A23: HOUR
A24: 0.57291667 | B24: =HOUR(A24) -> 13
A26: MINUTES
A27: 0.49305556 | B27: =MINUTE(A27) -> 50
A29: SECONDS
A30: 0.12891204 | B30: =SECOND(A30) -> 38
A32: DATE VAUE
A33: =DATEVALUE("05-09-2026") -> 46270 | B33: 46270
A35: TIME VALUE
A36: =TIMEVALUE("12:35 PM") -> 0.52430556 | B36: 0.52430556

Sheet COUNT Practice
A1: EXCEL COUNT, COUNTBLANK, COUNTIF & COUNTIFS PRACTICE
A2: NAME | B2: DEPARTMENT | C2: MARKS | D2: ATTENDANCE | E2: STATUS
A3: Aman | B3: Sales | C3: 78 | D3: 92 | E3: Pass
A4: Karan | B4: Sales | C4: 45 | D4: 75 | E4: Fail
A5: Neha | B5: IT | C5: 91 | D5: 96 | E5: Pass
A6: Rohit | B6: HR | D6: 82 | E6: Pending
A7: Pooja | B7: IT | C7: 72 | E7: Pass
A8: Vikas | B8: Sales | C8: 58 | D8: 85 | E8: Pass
A9: Simran | B9: HR | C9: 39 | D9: 70 | E9: Fail
A10: Meena | B10: Sales | D10: 89 | E10: Pending
A12: 4 CONDITIONS/QUESTIONS
A13: 1. COUNT | B13: How many values are there in the Marks column? | C13: =COUNT(C3:C10) -> 6
A14: 2. COUNTBLANK | B14: How many blank cells are there in the Marks column? | C14: =COUNTBLANK(C3:C10) -> 2
A15: 3. COUNTIF | B15: How many employees belong to the sales department? | C15: =COUNTIF(B3:B10,"sales") -> 4
A16: 4. COUNTIFS | B16: How many employees belong to the IT department and have marks greater than or equal to 80? | C16: =COUNTIFS(B3:B10,"IT",C3:C10,">=80") -> 1
A18: FORMULAS & ANSWERS
A19: COUNT | B19: 6
A20: COUNTBLANK | B20: 2
A21: COUNTIF | B21: 4
A22: COUNTIFS | B22: 1

Sheet Eligible-Not Eligible
A1: An employee will be eligible for the bonus if their performance score is 80 or above and they have achieved either the sales target or the project target. Otherwise, they will be Not Eligible.
A3: Employee ID | B3: Employee Name | C3: Perfomance Score | D3: Sales Target | E3: Project Target | F3: Result
A4: E001 | B4: Priya | C4: 85 | D4: Achieved | E4: Achieved | F4: =IF(AND(C4>=80,OR(D4="achieved",E4="achived")),"eligible","not eligible") -> eligible
A5: E002 | B5: Fathima | C5: 78 | D5: Achieved | E5: Achieved | F5: =IF(AND(C5>=80,OR(D5="achieved",E5="achieved")),"eligible","not eligible") -> not eligible
A6: E003 | B6: Angel | C6: 92 | D6: Not Achieved | E6: Achieved | F6: =IF(AND(C6>=80,OR(D6="achieved",E6="achieved")),"eligible","not eligible") -> eligible
A7: E004 | B7: Preethi | C7: 74 | D7: Not Achieved | E7: Not Achieved | F7: =IF(AND(C7>=80,OR(D7="achieved",E7="achieved")),"eligible","not eligible") -> not eligible
A8: E005 | B8: Kaviya | C8: 81 | D8: Achieved | E8: Not Achieved | F8: =IF(AND(C8>=80,OR(D8="achieved",E8="achieved")),"eligible","not eligible") -> eligible
A9: E006 | B9: Bhuvana | C9: 88 | D9: Not Achieved | E9: Not Achieved | F9: =IF(AND(C9>=80,OR(D9="achieved",E9="achieved")),"eligible","not eligible") -> not eligible
A10: E007 | B10: Merlin | C10: 79 | D10: Achieved | E10: Achieved | F10: =IF(AND(C10>=80,OR(D10="achieved",E10="achieved")),"eligible","not eligible") -> not eligible
A11: E008 | B11: Pavithra | C11: 95 | D11: Achieved | E11: Achieved | F11: =IF(AND(C11>=80,OR(D11="achieved",E11="achieved")),"eligible","not eligible") -> eligible
A12: E009 | B12: Monica | C12: 83 | D12: Not Achieved | E12: Achieved | F12: =IF(AND(C12>=80,OR(D12="achieved",E12="achieved")),"eligible","not eligible") -> eligible
A13: E010 | B13: Hema | C13: 69 | D13: Achieved | E13: Not Achieved | F13: =IF(AND(C13>=80,OR(D13="achieved",E13="achieved")),"eligible","not eligible") -> not eligible

Sheet FORMULAS(Beginners)
A1: FORMULA FOR EXCEL BEGINNERS
A2: NAME | B2: ENGLISH | C2: MATHS | D2: SCIENCE
A3: Aman | B3: 78 | C3: 83 | D3: 72
A4: Karan | B4: 92 | C4: 88 | D4: 95
A5: Neha | B5: 65 | C5: 74 | D5: 69
A6: Rohit | B6: 81 | C6: 79 | D6: 84
A7: Pooja | B7: 56 | C7: 63 | D7: 61
A8: Vikas | B8: 88 | C8: 91 | D8: 86
A9: Simran | B9: 73 | C9: 68 | D9: 77
A10: Meena | B10: 95 | C10: 94 | D10: 92
A12: MIN FORMULA | C12: =MIN(B3:B10) -> 56
A13: MAX FORMULA | C13: =MAX(C3:C10) -> 94
A14: AVERAGE FORMULA | C14: =AVERAGE(D3:D10) -> 79.5
A15: COUNT FORMULA | C15: =COUNT(B3:B10) -> 8

Sheet SUMIF, SUMIFS Practice
A1: SUMIF VS COUNTIF VS AVERAGEIF
A3: SUMIF | B3: =SUMIF(B8:B19,"NISHA",E8:E19) -> 26000
A4: COUNTIF | B4: =COUNTIF(B8:B19,"ARUN") -> 2
A5: AVERAGEIF | B5: =AVERAGEIF(B8:B19,"ARUN",E8:E19) -> 43000
A7: DATE | B7: SALES PERSON | C7: REGION | D7: PRODUCT | E7: SALES
A8: 46235 | B8: Silviya | C8: North | D8: Laptop | E8: 55000
A9: 46236 | B9: ARUN | C9: South | D9: Mobile | E9: 28000
A10: 46237 | B10: Priya | C10: North | D10: Laptop | E10: 62000
A11: 46238 | B11: Bhuvana | C11: West | D11: Tablet | E11: 32000
A12: 46239 | B12: Merlin | C12: North | D12: Mobile | E12: 24000
A13: 46240 | B13: Arun | C13: South | D13: Laptop | E13: 58000
A14: 46241 | B14: Nisha | C14: East | D14: Mobile | E14: 26000
A15: 46242 | B15: Priya | C15: West | D15: Laptop | E15: 61000
A16: 46243 | B16: Swetha | C16: North | D16: Tablet | E16: 35000
A17: 46244 | B17: Varun | C17: South | D17: Mobile | E17: 22000
A18: 46245 | B18: Swetha | C18: East | D18: Laptop | E18: 57000
A19: 46246 | B19: Hema | C19: West | D19: Mobile | E19: 25000

Sheet SUMIFS
A1: SUMIFS
A3: QUESTION | C3: FORMULA | D3: RESULT
A4: Total sales for Arun in South region | C4: =SUMIFS(E8:E19,B8:B19,"ARUN",C8:C19,"SOUTH") -> 86000 | D4: =SUMIFS(E8:E19,B8:B19,"arun",C8:C19,"south") -> 86000
A7: DATE | B7: SALES PERSON | C7: REGION | D7: PRODUCT | E7: SALES
A8: 46235 | B8: Silviya | C8: North | D8: Laptop | E8: 55000
A9: 46236 | B9: ARUN | C9: South | D9: Mobile | E9: 28000
A10: 46237 | B10: Priya | C10: North | D10: Laptop | E10: 62000
A11: 46238 | B11: Bhuvana | C11: West | D11: Tablet | E11: 32000
A12: 46239 | B12: Merlin | C12: North | D12: Mobile | E12: 24000
A13: 46240 | B13: Arun | C13: South | D13: Laptop | E13: 58000
A14: 46241 | B14: Nisha | C14: East | D14: Mobile | E14: 26000
A15: 46242 | B15: Priya | C15: West | D15: Laptop | E15: 61000
A16: 46243 | B16: Swetha | C16: North | D16: Tablet | E16: 35000
A17: 46244 | B17: Varun | C17: South | D17: Mobile | E17: 22000
A18: 46245 | B18: Swetha | C18: East | D18: Laptop | E18: 57000
A19: 46246 | B19: Hema | C19: West | D19: Mobile | E19: 25000

Sheet SUMIF VS SUM+FILTER FORMULA
A1: SUMIF VS SUM+FILTER FORMULA
A3: NAME | B3: SALES | C3: RM NAME | D3: TOWN
A4: Priya | B4: 13721 | C4: Rajesh Sharma | D4: Delhi
A5: Fathima | B5: 16267 | C5: Vikram Malhotrta | D5: Mumbai
A6: Angel | B6: 17273 | C6: Anita Roy | D6: Bangalore
A7: Preethi | B7: 17860 | C7: Rajesh Sharma | D7: Pune
A8: Kaviya | B8: 13213 | C8: Deepek Verma | D8: Ahmedabad
A9: Bhuvana | B9: 18689 | C9: Anita Roy | D9: Hyderabad
A10: Merlin | B10: 13645 | C10: Vikram Malhotrta | D10: Chennai
A11: Pavithra | B11: 15182 | C11: Deepek Verma | D11: Kolkata
A12: Monica | B12: 14463 | C12: Rajesh Sharma | D12: Lucknow
A13: Hema | B13: 16592 | C13: Anita Roy | D13: Jaipur
A15: NAME | B15: TOTAL SALES | D15: SUMIF FORMULA
A16: Priya | B16: =SUMIF(A4:A13,A4,B4:B13) -> 13721 | D16: =SUMIF(A4:A13,A9,B4:B13) -> 18689
A17: Fathima | B17: =SUMIF(A4:A13,A5,B4:B13) -> 16267
A18: Angel | B18: =SUMIF(A4:A13,A6,B4:B13) -> 17273 | D18: SUM+FILTER FORMULA
A19: Preethi | B19: =SUMIF(A4:A13,A7,B4:B13) -> 17860 | D19: {=SUM(_xlfn._xlws.FILTER(B4:B13,A4:A13=A7))} -> 17860

Sheet DATE VS EDATE FORMULA
A1: DATE VS EDATE FORMULA
A2: EMPLOYEE | B2: YEAR | C2: MONTH | D2: DAY | E2: MONTH TO ADD | F2: DATE FORMULA | G2: EDATE FORMULA
A3: Priya | B3: 2024 | C3: 1 | D3: 16 | E3: 21 | F3: =DATE(B3,C3,D3) -> 45307 | G3: =EDATE(F3,E3) -> 45946
A4: Fathima | B4: 2019 | C4: 2 | D4: 17 | E4: 22 | F4: =DATE(B4,C4,D4) -> 43513 | G4: =EDATE(F4,E4) -> 44182
A5: Angel | B5: 2018 | C5: 3 | D5: 18 | E5: 23 | F5: =DATE(B5,C5,D5) -> 43177 | G5: =EDATE(F5,E5) -> 43879
A6: Preethi | B6: 2020 | C6: 4 | D6: 19 | E6: 24 | F6: =DATE(B6,C6,D6) -> 43940 | G6: =EDATE(F6,E6) -> 44670
A7: Kaviya | B7: 2023 | C7: 5 | D7: 20 | E7: 25 | F7: =DATE(B7,C7,D7) -> 45066 | G7: =EDATE(F7,E7) -> 45828
A8: Bhuvana | B8: 2022 | C8: 6 | D8: 21 | E8: 26 | F8: =DATE(B8,C8,D8) -> 44733 | G8: =EDATE(F8,E8) -> 45525
A9: Merlin | B9: 2021 | C9: 7 | D9: 22 | E9: 27 | F9: =DATE(B9,C9,D9) -> 44399 | G9: =EDATE(F9,E9) -> 45221
A10: Pavithra | B10: 2016 | C10: 8 | D10: 23 | E10: 28 | F10: =DATE(B10,C10,D10) -> 42605 | G10: =EDATE(F10,E10) -> 43457
A11: Monica | B11: 2025 | C11: 9 | D11: 24 | E11: 29 | F11: =DATE(B11,C11,D11) -> 45924 | G11: =EDATE(F11,E11) -> 46807
A12: Hema | B12: 2017 | C12: 10 | D12: 25 | E12: 30 | F12: =DATE(B12,C12,D12) -> 43033 | G12: =EDATE(F12,E12) -> 43946

Sheet VLOOKUP 1
A1: EMPLOYER ID | B1: NAME | C1: DEPARTMENT | D1: SALARY | F1: VLOOKUP Search
A2: E001 | B2: Anjali | C2: Sales | D2: 25000 | F2: ENTER EMPLOYEE ID | G2: E003
A3: E002 | B3: Priya | C3: IT | D3: 30000
A4: E003 | B4: Kaviya | C4: HR | D4: 28000 | F4: NAME | G4: Kaviya
A5: E004 | B5: Maran | C5: Finance | D5: 27000 | F5: DEPARTMENT | G5: HR
A6: E005 | B6: Divya | C6: Operations | D6: 32000 | F6: SALARY | G6: =VLOOKUP(G2,A2:D6,4,FALSE) -> 28000

Sheet VLOOKUP 2
A1: RAW DATA EXTRACT | F1: PAY REPORT
A2: EMPLOYEE ID | B2: LAST NAME | C2: FIRST NAME | F2: EMPOYEE ID | G2: PAY | H2: FIRST NAME | I2: LAST NAME
A3: 110608 | B3: Doe | C3: John | F3: 990678 | G3: 84289 | H3: =VLOOKUP(F3,A3:C15,3,FALSE) -> Brad | I3: =VLOOKUP(F3,A3:C15,2,FALSE) -> Pitt
A4: 253072 | B4: Cline | C4: Andy | F4: 830385 | G4: 137670 | H4: =VLOOKUP(F4,A4:C16,3,FALSE) -> Prince | I4: =VLOOKUP(F4,A4:C16,2,FALSE) -> Williams
A5: 352711 | B5: Smith | C5: John | F5: 795574 | G5: 190024 | H5: =VLOOKUP(F5,A5:C17,3,FALSE) -> Tony | I5: =VLOOKUP(F5,A5:C17,2,FALSE) -> Stark
A6: 391006 | B6: Pan | C6: Peter | F6: 580622 | G6: 122604 | H6: =VLOOKUP(F6,A6:C18,3,FALSE) -> Eli | I6: =VLOOKUP(F6,A6:C18,2,FALSE) -> Manning
A7: 392128 | B7: Favre | C7: Bret | F7: 549457 | G7: 111709 | H7: =VLOOKUP(F7,A7:C19,3,FALSE) -> John | I7: =VLOOKUP(F7,A7:C19,2,FALSE) -> Elway
A8: 549457 | B8: Elway | C8: John | F8: 392128 | G8: 85931 | H8: =VLOOKUP(F8,A3:C15,3,FALSE) -> Bret | I8: =VLOOKUP(F8,A3:C15,2,FALSE) -> Favre
A9: 580622 | B9: Manning | C9: Eli | F9: 391006 | G9: 168114 | H9: =VLOOKUP(F9,A4:C16,3,FALSE) -> Peter | I9: =VLOOKUP(F9,A4:C16,2,FALSE) -> Pan
A10: 602693 | B10: Vick | C10: Micheal | F10: 352711 | G10: 89627 | H10: =VLOOKUP(F10,A5:C17,3,FALSE) -> John | I10: =VLOOKUP(F10,A5:C17,2,FALSE) -> Smith
A11: 611810 | B11: Woods | C11: Tiger | F11: 253072 | G11: 149946 | H11: =VLOOKUP(F11,A3:C15,3,FALSE) -> Andy | I11: =VLOOKUP(F11,A3:C15,2,FALSE) -> Cline
A12: 612235 | B12: Jordan | C12: Micheal | F12: 612235 | G12: 145893 | H12: =VLOOKUP(F12,A12:C24,3,FALSE) -> Micheal | I12: =VLOOKUP(F12,A7:C19,2,FALSE) -> Jordan
A13: 795574 | B13: Stark | C13: Tony | F13: 611810 | G13: 64757 | H13: =VLOOKUP(F13,A3:C15,3,FALSE) -> Tiger | I13: =VLOOKUP(F13,A8:C20,2,FALSE) -> Woods
A14: 830385 | B14: Williams | C14: Prince | F14: 602693 | G14: 71478 | H14: =VLOOKUP(F14,A4:C16,3,FALSE) -> Micheal | I14: =VLOOKUP(F14,A9:C21,2,FALSE) -> Vick
A15: 990678 | B15: Pitt | C15: Brad | F15: 110608 | G15: 131505 | H15: =VLOOKUP(F15,A3:C15,3,FALSE) -> John | I15: =VLOOKUP(F15,A3:C15,2,FALSE) -> Doe

Sheet VLOOKUP 3
A1: RAW DATA EXTRACT #1 | F1: PAY REPORT
F2: EMPOYEE ID | G2: PAY | H2: LAST NAME | I2: CITY
A3: EMPLOYEE ID | B3: LAST NAME | C3: FIRST NAME | F3: 990678 | G3: 84289 | H3: =VLOOKUP(F3,A4:C16,2,TRUE) -> Pitt | I3: =VLOOKUP(F3,A22:C34,2,TRUE) -> Austin
A4: 110608 | B4: Doe | C4: John | F4: 830385 | G4: 137670 | H4: =VLOOKUP(F4,A5:C17,2,TRUE) -> Williams | I4: =VLOOKUP(F4,A23:C35,2,TRUE) -> Chicago
A5: 253072 | B5: Cline | C5: Andy | F5: 795574 | G5: 190024 | H5: =VLOOKUP(F5,A6:C18,2,TRUE) -> Stark | I5: =VLOOKUP(F5,A24:C36,2,TRUE) -> Austin
A6: 352711 | B6: Smith | C6: John | F6: 580622 | G6: 122604 | H6: =VLOOKUP(F6,A7:C19,2,TRUE) -> Manning | I6: =VLOOKUP(F6,A25:C37,2,TRUE) -> Columbus
A7: 391006 | B7: Pan | C7: Peter | F7: 549457 | G7: 111709 | H7: =VLOOKUP(F7,A8:C20,2,TRUE) -> Elway | I7: =VLOOKUP(F7,A26:C38,2,TRUE) -> Tampa Bay
A8: 392128 | B8: Favre | C8: Bret | F8: 392128 | G8: 85931 | H8: =VLOOKUP(F8,A4:C16,2,TRUE) -> Favre | I8: =VLOOKUP(F8,A22:C34,2,TRUE) -> Chicago
A9: 549457 | B9: Elway | C9: John | F9: 391006 | G9: 168114 | H9: =VLOOKUP(F9,A5:C17,2,TRUE) -> Pan | I9: =VLOOKUP(F9,A23:C35,2,TRUE) -> Chicago
A10: 580622 | B10: Manning | C10: Eli | F10: 352711 | G10: 89627 | H10: =VLOOKUP(F10,A11:C23,2,TRUE) -> Chicago | I10: =VLOOKUP(F10,A24:C36,2,TRUE) -> Tampa Bay
A11: 602693 | B11: Vick | C11: Micheal | F11: 253072 | G11: 149946 | H11: =VLOOKUP(F11,A12:C24,2,TRUE) -> Chicago | I11: =VLOOKUP(F11,A22:C34,2,TRUE) -> Chicago
A12: 611810 | B12: Woods | C12: Tiger | F12: 612235 | G12: 145893 | H12: =VLOOKUP(F12,A13:C25,2,TRUE) -> Chicago | I12: =VLOOKUP(F12,A31:C43,2,TRUE) -> Tampa Bay
A13: 612235 | B13: Jordan | C13: Micheal | F13: 611810 | G13: 64757 | H13: =VLOOKUP(F13,A14:C26,2,TRUE) -> Chicago | I13: =VLOOKUP(F13,A22:C44,2,TRUE) -> Austin
A14: 795574 | B14: Stark | C14: Tony | F14: 602693 | G14: 71478 | H14: =VLOOKUP(F14,A15:C27,2,TRUE) -> Tampa Bay | I14: =VLOOKUP(F14,A22:C44,2,TRUE) -> Tampa Bay
A15: 830385 | B15: Williams | C15: Prince | F15: 110608 | G15: 131505 | H15: =VLOOKUP(F15,A16:C28,2,TRUE) -> Columbus | I15: =VLOOKUP(F15,A22:C45,2,TRUE) -> Columbus
A16: 990678 | B16: Pitt | C16: Brad
A19: RAW DATA EXTRACT #2
A21: EMPLOYEE ID | B21: CITY | C21: STATE
A22: 110608 | B22: Columbus | C22: Ohio
A23: 253072 | B23: Chicago | C23: Illnois
A24: 352711 | B24: Tampa Bay | C24: Florida
A25: 391006 | B25: Chicago | C25: Illnois
A26: 392128 | B26: Chicago | C26: Illnois
A27: 549457 | B27: Tampa Bay | C27: Florida
A28: 580622 | B28: Columbus | C28: Ohio
A29: 602693 | B29: Tampa Bay | C29: Florida
A30: 611810 | B30: Austin | C30: Texas
A31: 612235 | B31: Tampa Bay | C31: Florida
A32: 795574 | B32: Austin | C32: Texas
A33: 830385 | B33: Chicago | C33: Illnois
A34: 990678 | B34: Austin | C34: Texas

Sheet VLOOKUP 4
A1: PAY BAND TABLE | E1: PAY REPORT
E2: EMPOYEE ID | F2: PAY | G2: PAY BAND
A3: PAY MIN | B3: PAY BAND | E3: 990678 | F3: 84289 | G3: =VLOOKUP(E3,A4:B8,2,TRUE) -> Level E
A4: 25000 | B4: Level A | E4: 830385 | F4: 137670 | G4: =VLOOKUP(E4,A5:B9,2,TRUE) -> Level E
A5: 50000 | B5: Level B | E5: 795574 | F5: 190024 | G5: =VLOOKUP(E5,A6:B10,2,TRUE) -> Level E
A6: 75000 | B6: Level C | E6: 580622 | F6: 122604 | G6: =VLOOKUP(E6,A7:B11,2,TRUE) -> Level E
A7: 100000 | B7: Level D | E7: 549457 | F7: 111709 | G7: =VLOOKUP(E7,A8:B12,2,TRUE) -> Level E
A8: 150000 | B8: Level E | E8: 392128 | F8: 85931 | G8: =VLOOKUP(E8,A4:B8,2,TRUE) -> Level E
E9: 391006 | F9: 168114 | G9: =VLOOKUP(E9,A5:B9,2,TRUE) -> Level E
E10: 352711 | F10: 89627 | G10: =VLOOKUP(E10,A6:B10,2,TRUE) -> Level E
E11: 253072 | F11: 149946 | G11: =VLOOKUP(E11,A7:B11,2,TRUE) -> Level E
E12: 612235 | F12: 145893 | G12: =VLOOKUP(E12,A8:B12,2,TRUE) -> Level E
E13: 611810 | F13: 64757 | G13: =VLOOKUP(E13,A4:B8,2,TRUE) -> Level E
E14: 602693 | F14: 71478 | G14: =VLOOKUP(E14,A5:B9,2,TRUE) -> Level E
E15: 110608 | F15: 131505 | G15: =VLOOKUP(E15,A6:B10,2,TRUE) -> Level D

Sheet XLOOKUP
A1: XLOOKUP Practical
A3: EMPLOYEE ID | B3: EMPLOYEE NAME | C3: DEPARTMENT | D3: JOB ROLE | E3: SALARY | F3: LOCATION | G3: STATUS
A4: EMP101 | B4: Priya | C4: ITES | D4: Process Executive | E4: 18000 | F4: Chennai | G4: Active
A5: EMP102 | B5: Renuga | C5: HR | D5: HR Executive | E5: 22000 | F5: Chennai | G5: Active
A6: EMP103 | B6: Nandhini | C6: Finance | D6: Accounts Executive | E6: 25000 | F6: Bengaluru | G6: Active
A7: EMP104 | B7: Abi | C7: ITES | D7: Customer Support | E7: 20000 | F7: Chennai | G7: Active
A8: EMP105 | B8: Lavanya | C8: IT | D8: MIS Executive | E8: 28000 | F8: Chennai | G8: Active
A9: EMP106 | B9: Divya | C9: ITES | D9: Data Entey | E9: 17500 | F9: Coimbatore | G9: Inactive
A10: EMP107 | B10: Mini | C10: IT | D10: Support Engineer | E10: 30000 | F10: Hyderabad | G10: Active
A11: EMP108 | B11: Malar | C11: HR | D11: Recruiter | E11: 24000 | F11: Chennai | G11: Active
A12: EMP109 | B12: Sankari | C12: Finance | D12: Finance Associate | E12: 26000 | F12: Bengaluru | G12: Active
A13: EMP110 | B13: Dharshini | C13: ITES | D13: Email Support | E13: 19000 | F13: Chennai | G13: Active
A16: PRACTICAL LOOKUP
A17: Enter Employee ID | B17: EMP104 | C17: Employee Name | D17: =_xlfn.XLOOKUP(B17,A4:A13,B4:B13,"NOT FOUND") -> Abi
A18: Enter Employee ID | B18: EMP107 | C18: Department | D18: =_xlfn.XLOOKUP(B18,A4:A13,C4:C13,"NOT FOUND") -> IT
A19: Enter Employee ID | B19: EMP105 | C19: Salary | D19: =_xlfn.XLOOKUP(B19,A4:A13,E4:E13,"NOT FOUND") -> 28000
A20: Enter Employee ID | B20: EMP110 | C20: Location | D20: =_xlfn.XLOOKUP(B20,A4:A13,F4:F13,"NOT FOUND") -> Chennai
A21: Enter Employee ID | B21: EMP102 | C21: Job Role | D21: =_xlfn.XLOOKUP(B21,A4:A13,D4:D13,"NOT FOUND") -> HR Executive

Sheet HLOOKUP
A1: HLOOKUP PRACTICAL EXCEL SHEET
A3: EMPLOYEE ID | B3: EMP001 | C3: EMP002 | D3: EMP003 | E3: EMP004 | F3: EMP005
A4: EMPLOYEE NAME | B4: Priya | C4: Renuga | D4: Lavanya | E4: Nandhini | F4: Abi
A5: DEPARTMENT | B5: Salea | C5: HR | D5: ITES | E5: Finance | F5: Support
A6: MONTHLY SALARY | B6: 22000 | C6: 25000 | D6: 33000 | E6: 28000 | F6: 24000
A8: LOOKUP EMPLOYEE ID | B8: EMP003
A9: EMPLOYEE NAME | B9: =HLOOKUP(B8,B3:F6,2,FALSE) -> Lavanya
A10: DEPARTMENT | B10: =HLOOKUP(B8,B3:F6,3,FALSE) -> ITES
A11: MONTHLY SALARY | B11: =HLOOKUP(B8,B3:F6,4,FALSE) -> 33000
A14: PRODUCT | B14: P001 | C14: P002 | D14: P003 | E14: P004 | F14: P005
A15: PRODUCT NAME | B15: Keuboard | C15: Mouse | D15: Headset | E15: Monitor | F15: Webcam
A16: CATEGORY | B16: IT | C16: IT | D16: Audio | E16: Display | F16: Camera
A17: PRICE | B17: 850 | C17: 450 | D17: 1200 | E17: 9500 | F17: 1800
A19: LOOKUP PRODUCT ID | B19: P004
A20: PRODUCT NAME | B20: =HLOOKUP(B19,B14:F17,2,FALSE) -> Monitor
A21: CATEGORY | B21: =HLOOKUP(B19,B14:F17,3,FALSE) -> Display
A22: PRICE | B22: =HLOOKUP(B19,B14:F17,4,FALSE) -> 9500

Sheet LOOKUP FORMULA
A1: EMPLOYEE MASTER DATA
A3: EMPLOYEE ID | B3: EMPLOYEE NAME | C3: DEPARTMENT | D3: DESIGNATION | E3: SALARY | F3: LOCATION | G3: JOINING DATE | H3: STATUS
A4: EMP101 | B4: Priya | C4: ITES | D4: Process Executive | E4: 18000 | F4: Chennai | G4: 45453 | H4: Active
A5: EMP102 | B5: Renuga | C5: HR | D5: HR Executive | E5: 22000 | F5: Chennai | G5: 45159 | H5: Active
A6: EMP103 | B6: Nandhini | C6: Finance | D6: Accounts Executive | E6: 25000 | F6: Bengaluru | G6: 44880 | H6: Active
A7: EMP104 | B7: Abi | C7: ITES | D7: Customer Support | E7: 20000 | F7: Chennai | G7: 45299 | H7: Active
A8: EMP105 | B8: Lavanya | C8: IT | D8: MIS Executive | E8: 28000 | F8: Chennai | G8: 44396 | H8: Active
A9: EMP106 | B9: Divya | C9: ITES | D9: Data Entey | E9: 17500 | F9: Coimbatore | G9: 45012 | H9: Inactive
A10: EMP107 | B10: Mini | C10: IT | D10: Support Engineer | E10: 30000 | F10: Hyderabad | G10: 45537 | H10: Active
A11: EMP108 | B11: Malar | C11: HR | D11: Recruiter | E11: 24000 | F11: Chennai | G11: 44711 | H11: Active
A12: EMP109 | B12: Sankari | C12: Finance | D12: Finance Associate | E12: 26000 | F12: Bengaluru | G12: 45271 | H12: Active
A13: EMP110 | B13: Dharshini | C13: ITES | D13: Email Support | E13: 19000 | F13: Chennai | G13: 44109 | H13: Active
A16: VLOOKUP FORMULA
A17: EMPLOYEE ID | B17: EMPLOYEE NAME | C17: DEPARTMENT | D17: DESIGNATION | E17: SALARY | F17: LOCATION | G17: JOINING DATE | H17: STATUS
A18: EMP106 | B18: =VLOOKUP(A18,A4:H13,2,FALSE) -> Divya | C18: =VLOOKUP(A18,A4:H13,3,FALSE) -> ITES | D18: =VLOOKUP(A18,A4:H13,4,FALSE) -> Data Entey | E18: =VLOOKUP(A18,A4:H13,5,FALSE) -> 17500 | F18: =VLOOKUP(A18,A4:H13,6,FALSE) -> Coimbatore | G18: =VLOOKUP(A18,A4:H13,7,FALSE) -> 45012 | H18: =VLOOKUP(A18,A4:H13,8,FALSE) -> Inactive
A21: XLOOKUP FORMULA
A22: Enter Employee ID | B22: EMP104 | C22: Employee Name | D22: =_xlfn.XLOOKUP(B22,A4:A13,B4:B13,"not found") -> Abi
A23: Enter Employee ID | B23: EMP107 | C23: Department | D23: =_xlfn.XLOOKUP(B23,A4:A13,C4:C13,"not found") -> IT
A24: Enter Employee ID | B24: EMP105 | C24: Designation | D24: =_xlfn.XLOOKUP(B24,A4:A13,D4:D13,"not found") -> MIS Executive
A25: Enter Employee ID | B25: EMP110 | C25: Salary | D25: =_xlfn.XLOOKUP(B25,A4:A13,E4:E13,"not found") -> 19000
A26: Enter Employee ID | B26: EMP102 | C26: Location | D26: =_xlfn.XLOOKUP(B26,A4:A13,F4:F13,"not found") -> Chennai
A29: HLOOKUP FORMULA
A31: EMPLOYEE ID | B31: EMP001 | C31: EMP002 | D31: EMP003 | E31: EMP004 | F31: EMP005
A32: EMPLOYEE NAME | B32: Priya | C32: Renuga | D32: Lavanya | E32: Nandhini | F32: Abi
A33: DEPARTMENT | B33: Salea | C33: HR | D33: ITES | E33: Finance | F33: Support
A34: MONTHLY SALARY | B34: 22000 | C34: 25000 | D34: 33000 | E34: 28000 | F34: 24000
A35: DESIGNATION | B35: Process Executive | C35: HR Executive | D35: Accounts Executive | E35: Customer Support | F35: Data Entey
A36: LOCATION | B36: Chennai | C36: Bengaluru | D36: Chennai | E36: Hyderabad | F36: Coimbatore
A38: LOOKUP EMPLOYEE ID | B38: EMP003
A39: EMPLOYEE NAME | B39: =HLOOKUP(B38,B31:F36,2,FALSE) -> Lavanya
A40: DEPARTMENT | B40: =HLOOKUP(B38,B31:F36,3,FALSE) -> ITES
A41: MONTHLY SALARY | B41: =HLOOKUP(B38,B31:F36,4,FALSE) -> 33000
A42: DESIGNATION | B42: =HLOOKUP(B38,B31:F36,5,FALSE) -> Accounts Executive
A43: LOCATION | B43: =HLOOKUP(B38,B31:F36,6,FALSE) -> Chennai

Sheet INDEX FUNCTION
A1: INDEX FUNCTION
A2: S.NO: | B2: PRODUCT | C2: RATE | D2: 2kg | E2: 5kg | F2: 10kg
A3: 1 | B3: Wheat | C3: 22 | D3: 44 | E3: 110 | F3: 220
A4: 2 | B4: Oil | C4: 122 | D4: 244 | E4: 610 | F4: 1220
A5: 3 | B5: Sugar | C5: 50 | D5: 100 | E5: 250 | F5: 500
A6: 4 | B6: Rice | C6: 68 | D6: 136 | E6: 340 | F6: 680
A7: 5 | B7: Salt | C7: 18 | D7: 36 | E7: 90 | F7: 180
A8: 6 | B8: Corn | C8: 42 | D8: 84 | E8: 210 | F8: 420
A9: 7 | B9: Oats | C9: 190 | D9: 380 | E9: 950 | F9: 1900
A10: 8 | B10: Amaranth | C10: 60 | D10: 120 | E10: 300 | F10: 600
A11: 9 | B11: Barley | C11: 400 | D11: 800 | E11: 2000 | F11: 4000
A12: 10 | B12: Bulgur | C12: 30 | D12: 60 | E12: 150 | F12: 300
A15: INDEX FUNCTION
A16: Rice (Row) | C16: =INDEX(B3:B12,4) -> Rice
A17: Rice (Row + Col) | C17: =INDEX(B3:F12,4,3) -> 136

Sheet MATCH FUNCTION
A1: MATCH FUNCTION
A2: S.NO: | B2: PRODUCT | C2: RATE | D2: 2kg | E2: 5kg | F2: 10kg
A3: 1 | B3: Wheat | C3: 22 | D3: 44 | E3: 110 | F3: 220
A4: 2 | B4: Oil | C4: 122 | D4: 244 | E4: 610 | F4: 1220
A5: 3 | B5: Sugar | C5: 50 | D5: 100 | E5: 250 | F5: 500
A6: 4 | B6: Rice | C6: 68 | D6: 136 | E6: 340 | F6: 680
A7: 5 | B7: Salt | C7: 18 | D7: 36 | E7: 90 | F7: 180
A8: 6 | B8: Corn | C8: 42 | D8: 84 | E8: 210 | F8: 420
A9: 7 | B9: Oats | C9: 190 | D9: 380 | E9: 950 | F9: 1900
A10: 8 | B10: Amaranth | C10: 60 | D10: 120 | E10: 300 | F10: 600
A11: 9 | B11: Barley | C11: 400 | D11: 800 | E11: 2000 | F11: 4000
A12: 10 | B12: Bulgur | C12: 30 | D12: 60 | E12: 150 | F12: 300
A15: MATCH FUNCTION
A16: Find Rice row number | C16: =MATCH("rice",B3:B12,0) -> 4
A17: Find 10kg column | C17: =MATCH("10kg",D2:F2,0) -> 3

Sheet INDEX + MATCH FUNCTION
A1: INDEX + MATCH FUNCTION
A3: S.NO: | B3: PRODUCT | C3: RATE | D3: 2kg | E3: 5kg | F3: 10kg
A4: 1 | B4: Wheat | C4: 22 | D4: 44 | E4: 110 | F4: 220
A5: 2 | B5: Oil | C5: 122 | D5: 244 | E5: 610 | F5: 1220
A6: 3 | B6: Sugar | C6: 50 | D6: 100 | E6: 250 | F6: 500
A7: 4 | B7: Rice | C7: 68 | D7: 136 | E7: 340 | F7: 680
A8: 5 | B8: Salt | C8: 18 | D8: 36 | E8: 90 | F8: 180
A9: 6 | B9: Corn | C9: 42 | D9: 84 | E9: 210 | F9: 420
A10: 7 | B10: Oats | C10: 190 | D10: 380 | E10: 950 | F10: 1900
A11: 8 | B11: Amaranth | C11: 60 | D11: 120 | E11: 300 | F11: 600
A12: 9 | B12: Barley | C12: 400 | D12: 800 | E12: 2000 | F12: 4000
A13: 10 | B13: Bulgur | C13: 30 | D13: 60 | E13: 150 | F13: 300
A16: INDEX + MATCH FUNCTION
A17: Product | C17: RicE
A18: Weight | C18: 10kg
A19: Result | C19: =INDEX(D4:F13,MATCH(C17,B4:B13,0),MATCH(C18,D3:F3,0)) -> 680
A22: PRACTICE
A23: Find Wheat 5kg price | C23: =INDEX(D4:F13,MATCH(B4,B4:B13,0),MATCH(E3,D3:F3,0)) -> 110
A24: Find Barley 2kg price | C24: =INDEX(D4:F13,MATCH(B12,B4:B13,0),MATCH(D3,D3:F3,0)) -> 800
A25: Find Oats 10kg price | C25: =INDEX(D4:F13,MATCH(B10,B4:B13,0),MATCH(F3,D3:F3,0)) -> 1900

Sheet  DATA VALIDATION & FILTER
A1: DATA VALIDATION & FILTER
A2: DATE | B2: EMPLOYEE | C2: DEPARTMENT | D2: LOCATION | E2: PRODUCT | F2: QUANTITY | G2: UNIT PRICE | H2: SALES AMOUNT
A3: 46027 | B3: Asha | C3: Customer Support | D3: Chennai | E3: Laptop | F3: 3 | G3: 45000 | H3: 135000
A4: 46030 | B4: Ravi | C4: Sales | D4: Bangalore | E4: Monitor | F4: 5 | G4: 12000 | H4: 60000
A5: 46034 | B5: Priya | C5: Customer Support | D5: Chennai | E5: Keyboard | F5: 10 | G5: 1500 | H5: 15000
A6: 46037 | B6: Kiran | C6: Technical Support | D6: Hyderabad | E6: Laptop | F6: 2 | G6: 45000 | H6: 90000
A7: 46042 | B7: Meena | C7: Sales | D7: Chennai | E7: Mouse | F7: 15 | G7: 800 | H7: 12000
A8: 46056 | B8: Asha | C8: Customer Support | D8: Bangalore | E8: Monitor | F8: 4 | G8: 12000 | H8: 48000
A9: 46060 | B9: Ravi | C9: Sales | D9: Chennai | E9: Laptop | F9: 2 | G9: 45000 | H9: 90000
A10: 46064 | B10: Priya | C10: Customer Support | D10: Hyderabad | E10: Mouse | F10: 20 | G10: 800 | H10: 16000
A11: 46071 | B11: Kiran | C11: Technical Support | D11: Bangalore | E11: Keyboard | F11: 12 | G11: 1500 | H11: 18000
A12: 46077 | B12: Meena | C12: Sales | D12: Hyderabad | E12: Monitor | F12: 6 | G12: 12000 | H12: 72000
A13: 46085 | B13: Asha | C13: Customer Support | D13: Chennai | E13: Laptop | F13: 1 | G13: 45000 | H13: 45000
A14: 46090 | B14: Ravi | C14: Sales | D14: Bangalore | E14: Mouse | F14: 25 | G14: 800 | H14: 20000
... A17: 46103 | B17: Meena | C17: Sales | D17: Chennai | E17: Keyboard | F17: 15 | G17: 1500 | H17: 22500

Sheet PIVOT TABLE & CHART
A1: PIVOT TABLE
A3: Row Labels | B3: Sum of UNIT PRICE | C3: Sum of SALES AMOUNT | D3: Sum of QUANTITY
A4: 46027 | B4: 45000 | C4: 135000 | D4: 3
A5: Asha | B5: 45000 | C5: 135000 | D5: 3
A6: 46030 | B6: 12000 | C6: 60000 | D6: 5 | F6: PIVOT CHART
A7: Ravi | B7: 12000 | C7: 60000 | D7: 5
A8: 46034 | B8: 1500 | C8: 15000 | D8: 10
A9: Priya | B9: 1500 | C9: 15000 | D9: 10
A10: 46037 | B10: 45000 | C10: 90000 | D10: 2
A11: Kiran | B11: 45000 | C11: 90000 | D11: 2
A12: 46042 | B12: 800 | C12: 12000 | D12: 15
A13: Meena | B13: 800 | C13: 12000 | D13: 15
A14: 46056 | B14: 12000 | C14: 48000 | D14: 4
A15: Asha | B15: 12000 | C15: 48000 | D15: 4
A16: 46060 | B16: 45000 | C16: 90000 | D16: 2
A17: Ravi | B17: 45000 | C17: 90000 | D17: 2
A18: 46064 | B18: 800 | C18: 16000 | D18: 20
A19: Priya | B19: 800 | C19: 16000 | D19: 20
A20: 46071 | B20: 1500 | C20: 18000 | D20: 12
A21: Kiran | B21: 1500 | C21: 18000 | D21: 12
A22: 46077 | B22: 12000 | C22: 72000 | D22: 6
A23: Meena | B23: 12000 | C23: 72000 | D23: 6
A24: 46085 | B24: 45000 | C24: 45000 | D24: 1
A25: Asha | B25: 45000 | C25: 45000 | D25: 1
A26: 46090 | B26: 800 | C26: 20000 | D26: 25
A27: Ravi | B27: 800 | C27: 20000 | D27: 25
A28: 46094 | B28: 12000 | C28: 36000 | D28: 3
A29: Priya | B29: 12000 | C29: 36000 | D29: 3
A30: 46098 | B30: 45000 | C30: 135000 | D30: 3
A31: Kiran | B31: 45000 | C31: 135000 | D31: 3
A32: 46103 | B32: 1500 | C32: 22500 | D32: 15
A33: Meena | B33: 1500 | C33: 22500 | D33: 15
A34: Grand Total | B34: 279900 | C34: 814500 | D34: 126

Sheet SALES DATA
A1: DATA VALIDATION & FILTER
A2: DATE | B2: EMPLOYEE | C2: DEPARTMENT | D2: LOCATION | E2: PRODUCT | F2: QUANTITY | G2: UNIT PRICE | H2: SALES AMOUNT
A3: 46027 | B3: Asha | C3: Customer Support | D3: Chennai | E3: Laptop | F3: 3 | G3: 45000 | H3: 135000
A4: 46030 | B4: Ravi | C4: Sales | D4: Bangalore | E4: Monitor | F4: 5 | G4: 12000 | H4: 60000
A5: 46034 | B5: Priya | C5: Customer Support | D5: Chennai | E5: Keyboard | F5: 10 | G5: 1500 | H5: 15000
A6: 46037 | B6: Kiran | C6: Technical Support | D6: Hyderabad | E6: Laptop | F6: 2 | G6: 45000 | H6: 90000
A7: 46042 | B7: Meena | C7: Sales | D7: Chennai | E7: Mouse | F7: 15 | G7: 800 | H7: 12000
A8: 46056 | B8: Asha | C8: Customer Support | D8: Bangalore | E8: Monitor | F8: 4 | G8: 12000 | H8: 48000
A9: 46060 | B9: Ravi | C9: Sales | D9: Chennai | E9: Laptop | F9: 2 | G9: 45000 | H9: 90000
A10: 46064 | B10: Priya | C10: Customer Support | D10: Hyderabad | E10: Mouse | F10: 20 | G10: 800 | H10: 16000
A11: 46071 | B11: Kiran | C11: Technical Support | D11: Bangalore | E11: Keyboard | F11: 12 | G11: 1500 | H11: 18000
A12: 46077 | B12: Meena | C12: Sales | D12: Hyderabad | E12: Monitor | F12: 6 | G12: 12000 | H12: 72000
A13: 46085 | B13: Asha | C13: Customer Support | D13: Chennai | E13: Laptop | F13: 1 | G13: 45000 | H13: 45000
A14: 46090 | B14: Ravi | C14: Sales | D14: Bangalore | E14: Mouse | F14: 25 | G14: 800 | H14: 20000
... A17: 46103 | B17: Meena | C17: Sales | D17: Chennai | E17: Keyboard | F17: 15 | G17: 1500 | H17: 22500

Sheet Column Chart
A3: Row Labels | B3: Sum of SALES AMOUNT
A4: Customer Support | B4: 295000
A5: Sales | B5: 276500
A6: Technical Support | B6: 243000
A7: Grand Total | B7: 814500

Sheet Pie Chart
A3: P | B3: Sum of UNIT PRICE
A4: Keyboard | B4: 4500
A5: Laptop | B5: 225000
A6: Monitor | B6: 48000
A7: Mouse | B7: 2400
A8: Grand Total | B8: 279900

Sheet Bar Chart
A3: Row Labels | B3: Sum of QUANTITY
A4: Bangalore | B4: 46
A5: Chennai | B5: 49
A6: Hyderabad | B6: 31
A7: Grand Total | B7: 126

Sheet Area Chart
A3: Row Labels | B3: Sum of SALES AMOUNT
A4: Asha | B4: 228000
A5: Kiran | B5: 243000
A6: Meena | B6: 106500
A7: Priya | B7: 67000
A8: Ravi | B8: 170000
A9: Grand Total | B9: 814500

Sheet 3D Pie Chart
A3: Row Labels | B3: Sum of SALES AMOUNT
A4: Jan | B4: 312000
A5: Feb | B5: 244000
A6: Mar | B6: 258500
A7: Grand Total | B7: 814500

Sheet  2D Line Chart
A3: Sum of QUANTITY | B3: Column Labels
A4: Row Labels | B4: Keyboard | C4: Laptop | D4: Monitor | E4: Mouse | F4: Grand Total
A5: Customer Support | B5: 10 | C5: 4 | D5: 7 | E5: 20 | F5: 41
A6: Sales | B6: 15 | C6: 2 | D6: 11 | E6: 40 | F6: 68
A7: Technical Support | B7: 12 | C7: 5 | F7: 17
A8: Grand Total | B8: 37 | C8: 11 | D8: 18 | E8: 60 | F8: 126

Sheet DASHBOARD
A1: DASHBOARD

Sheet PIVOT TABLE SUMMARY
A1: PIVOT TABLE SUMMARY
A2: SALES BY DEPARTMENT | C2: SALES BY PRODUCT | E2: QUANTITY BY LOCATION
A3: DEPARTMENT | B3: TOTAL SALES | C3: PRODUCT | D3: TOTAL SALES | E3: LOCATION | F3: TOTAL SALES
A4: CUSTOMER SUPPORT | B4: =SUMIF('SALES DATA'!C3:C17,'PIVOT TABLE SUMMARY'!A4,'SALES DATA'!H3:H17) -> 295000 | C4: LAPTOP | D4: =SUMIF('SALES DATA'!E3:E17,'PIVOT TABLE SUMMARY'!C4,'SALES DATA'!H3:H17) -> 495000 | E4: CHENNAI | F4: =SUMIF('SALES DATA'!D3:D17,'PIVOT TABLE SUMMARY'!E4,'SALES DATA'!F3:F17) -> 49
A5: SALES | B5: =SUMIF('SALES DATA'!C4:C18,'PIVOT TABLE SUMMARY'!A5,'SALES DATA'!H4:H18) -> 276500 | C5: MONITOR | D5: =SUMIF('SALES DATA'!E4:E18,'PIVOT TABLE SUMMARY'!C5,'SALES DATA'!H4:H18) -> 216000 | E5: BANGALORE | F5: =SUMIF('SALES DATA'!D4:D18,'PIVOT TABLE SUMMARY'!E5,'SALES DATA'!F4:F18) -> 46
A6: TECHNICAL SUPPORT | B6: =SUMIF('SALES DATA'!C5:C19,'PIVOT TABLE SUMMARY'!A6,'SALES DATA'!H5:H19) -> 243000 | C6: KEYBOARD | D6: =SUMIF('SALES DATA'!E5:E19,'PIVOT TABLE SUMMARY'!C6,'SALES DATA'!H5:H19) -> 0 | E6: HYDERABAD | F6: =SUMIF('SALES DATA'!D5:D19,'PIVOT TABLE SUMMARY'!E6,'SALES DATA'!F5:F19) -> 31
C7: MOUSE | D7: =SUMIF('SALES DATA'!E6:E20,'PIVOT TABLE SUMMARY'!C7,'SALES DATA'!H6:H20) -> 48000
